{
    "$schema": "https://schema.management.azure.com/schemas/2015-01-01/deploymentParameters.json#",
    "contentVersion": "1.0.0.0",
    "parameters": {
        "AdminPassword": {
            "value": ""
        },
        "VirtualMachineName": {
            "value": "paku1604c1"
        },
        "NetworkCardName": {
            "value": "pakunic1"
        },
        "NetworkSecurityGroupName": {
            "value": "blogcnt"
        },
        "PublicIPName": {
            "value": "paku1604c1"
        },
        "VnetName": {
            "value": "paku1604vnet"
        },
        "StorageAccount": {
            "value": "paku1604c"
        }
    }
}